{"author":"brooder","content":"首页","desc":"首页","editable":true,"id":"index","keywords":"test","logo":"","pageurl":"","sort":"main","template":"<!DOCTYPE html>\n<html>\n  \n  <head>\n    <meta charset=\"UTF-8\">\n    <meta name=\"viewport\" content=\"width=device-width, initial-scale=1.0, minimum-scale=1.0, user-scalable=no\"\n    />\n    <meta name=\"format-detection\" content=\"telephone=no\">\n    <meta name=\"apple-mobile-web-app-status-bar-style\" content=\"white\">\n    <meta name=\"apple-mobile-web-app-capable\" content=\"yes\" />\n    <link rel=\"apple-touch-icon-precomposed\" sizes=\"144x144\" href=\"${httpPath}/assets/icons/144.png\">\n    <link rel=\"apple-touch-icon-precomposed\" sizes=\"114x114\" href=\"${httpPath}/assets/icons/114.png\">\n    <link rel=\"apple-touch-icon-precomposed\" sizes=\"72x72\" href=\"${httpPath}/assets/icons/72.png\">\n    <link rel=\"apple-touch-icon-precomposed\" sizes=\"57x57\" href=\"${httpPath}/assets/icons/57.png\">\n    <link rel=\"shortcut icon\" href=\"${httpPath}/assets/icons/144.png\">\n    <title>\n      ${Option.title}\n    <\/title>\n    <script src=\"${httpPath}assets/brooder.core.js\" type=\"text/javascript\">\n    <\/script>\n    <link rel=\"stylesheet\" href=\"${httpPath}assets/packets/page/css/grid.css\">\n    <link rel=\"stylesheet\" href=\"${httpPath}assets/packets/page/css/default.css\">\n    <script>\n      $().ready(function() {\n        window.basePath = \"${httpPath}\";\n        $(\"body\").Boot({\n          basePath: \"${httpPath}assets/packets/\"\n        });\n      });\n    <\/script>\n  <\/head>\n  \n  <body><div class=\"row\"><div class=\"span1-1\"><@module id=\"navigator\"><\/@module><\/div><\/div><div class=\"row\"><div class=\"span1-1\"><@module id=\"32d66a6943154588\"><\/@module><\/div><\/div><div class=\"row\"><div class=\"span1-1\"><@module id=\"c0ea8254a1d04961\"><\/@module><\/div><\/div><div class=\"row\"><div class=\"span1-1\" ><@module id=\"a3a1c61f90b14c0f\"><\/@module><@module id=\"11d25e64d8bf4070\"><\/@module><\/div><\/div><div class=\"row\"><div class=\"span1-1\"><@module id=\"397052bde8fd4d8f\"><\/@module><\/div><\/div><div class=\"row\"><div class=\"span1-1\"><@module id=\"5d2ddc1aca8d48e4\"><\/@module><\/div><\/div><div class=\"row\"><div class=\"span1-1\"><@module id=\"177baf33e99644b6\"><\/@module><\/div><\/div><div class=\"row\"><div class=\"span1-1\"><@module id=\"56c02cdc50894245\"><\/@module><\/div><\/div><div class=\"row\"><div class=\"span1-1\"><@module id=\"map\"><\/@module><\/div><\/div><div class=\"row\"><div class=\"span1-1\"><@module id=\"footer\"><\/@module><\/div><\/div><div class=\"row\"><div class=\"span1-1\"><@module id=\"copyright\"><\/@module><\/div><\/div><\/body>\n\n<\/html>","title":"首页"}