{"desc":"产品列表","editSetting":"{\"width\":600}","editable":true,"fields":"[{\"type\":\"contenter.form.select\",\"name\":\"background\",\"label\":\"背景色\",\"value\":\"grey\",\"defaults\":[{\"key\":\"灰色\",\"value\":\"grey\"},{\"key\":\"白色\",\"value\":\"white\"}]},{\"type\":\"contenter.form.text\",\"name\":\"title\",\"label\":\"标题\",\"value\":\"核心产品\"},{\"type\":\"contenter.form.text\",\"name\":\"desc\",\"label\":\"描述\",\"value\":\"下面是公司的核心产品\"},{\"type\":\"contenter.form.extendform\",\"label\":\"产品页面配置\",\"name\":\"links\",\"value\":[{\"pagename\":\"index\",\"pic\":\"assets/packets/page/css/images/yy.png\",\"title\":\"产品名称\",\"desc\":\"产品描述\"}],\"fields\":[{\"type\":\"contenter.form.imageupload\",\"label\":\"图片\",\"name\":\"pic\"},{\"type\":\"contenter.form.pagelist\",\"label\":\"产品页面\",\"name\":\"pagename\"},{\"type\":\"contenter.form.text\",\"label\":\"产品名称\",\"name\":\"title\"},{\"type\":\"contenter.form.text\",\"label\":\"产品描述\",\"name\":\"desc\"}]},{\"type\":\"contenter.form.select\",\"name\":\"type\",\"label\":\"显示模式\",\"value\":\"single\",\"defaults\":[{\"key\":\"缩略显示\",\"value\":\"single\"},{\"key\":\"全部信息\",\"value\":\"all\"}]}]","icon":"assets/icons/2ee5aaf75ea743c1.png","removeable":true,"single":false,"sort":"product","template":"<div class=\"optb ${Values.background}\">\r\n    <#if Values.type=='single'>\r\n        <div class=\"row mid-fix\">\r\n            <div class=\"optb-title\">${Values.title}<\/div>\r\n            <div class=\"optb-desc\">${Values.desc}<\/div>\r\n        <\/div>\r\n        <#assign json=Values.links?eval />\r\n        <div class=\"row mid-fix on768-row-2col on480-row-1col\">\r\n            <#list json as item>\r\n                <div class=\"span1-4\">\r\n                    <a href=\"${httpPath}pages/${item.pagename}\"><img src=\"${httpPath}${item.pic}\" alt=\"\"/><\/a>\r\n                <\/div>\r\n            <\/#list>\r\n        <\/div>\r\n    <#else>\r\n        <#assign json=Values.links?eval />\r\n        <div class=\"row mid-fix on768-row-2col on480-row-1col\">\r\n            <#list json as item>\r\n                <div class=\"span1-3\">\r\n                    <div class=\"optb-inner\">\r\n                        <div class=\"optb-inner-img\">\r\n                            <img src=\"${httpPath}${item.pic}\" alt=\"\"/>\r\n                        <\/div>\r\n                        <div class=\"optb-inner-title\">${item.title}<\/div>\r\n                        <div class=\"optb-inner-desc\">${item.desc}<\/div>\r\n                        <div class=\"optb-inner-link\"><a href=\"${httpPath}pages/${item.pagename}\">查看详情<\/a><\/div>\r\n                    <\/div>\r\n                <\/div>\r\n            <\/#list>\r\n        <\/div>\r\n    <\/#if>\r\n<\/div>","type":"products","values":"{\"title\":\"核心产品\",\"desc\":\"下面是公司的核心产品\",\"background\":\"grey\",\"links\":\"[{\\\"pagename\\\":\\\"index\\\",\\\"pic\\\":\\\"assets/packets/page/css/images/yy.png\\\",\\\"title\\\":\\\"产品名称\\\",\\\"desc\\\":\\\"产品描述\\\"}]\",\"type\":\"single\"}","version":"1.0","view":"page.base.basepagemodule"}